MailChecker.py
mailchecker-6.0.19.dist-info/METADATA
mailchecker-6.0.19.dist-info/WHEEL
mailchecker-6.0.19.dist-info/top_level.txt
mailchecker-6.0.19.dist-info/RECORD
