Metadata-Version: 2.4
Name: mailchecker
Version: 6.0.19
Summary: Cross-language temporary email detection library. Stop users from signing up with temporary email addresses.
Home-page: https://github.com/FGRibreau/mailchecker
Author: Francois-Guillaume Ribreau
Author-email: github@fgribreau.com
Classifier: Programming Language :: Python :: 3
Classifier: License :: OSI Approved :: MIT License
Classifier: Operating System :: OS Independent
Requires-Python: >=3.6
Dynamic: author
Dynamic: author-email
Dynamic: classifier
Dynamic: home-page
Dynamic: requires-python
Dynamic: summary
